Metadata-Version: 1.1
Name: mandrill-37
Version: 1.1.0
Summary: A CLI client and Python API library for the Mandrill email as a service platform. Forked fork python 3.7 support
Home-page: https://bitbucket.org/mailchimp/mandrill-api-python/
Author: Mandrill Devs. Forked by Florian Mounier
Author-email: community@mandrill.com
License: Apache-2.0
Keywords: mandrill email api
Platform: UNKNOWN
Classifier: Development Status :: 4 - Beta
Classifier: Environment :: Console
Classifier: Intended Audience :: Developers
Classifier: Intended Audience :: System Administrators
Classifier: License :: OSI Approved :: Apache Software License
Classifier: Topic :: Communications :: Email
Provides: m
Provides: a
Provides: n
Provides: d
Provides: r
Provides: i
Provides: l
Provides: l
